setup.cfg
setup.py
mozhginfo/__init__.py
mozhginfo/push.py
mozhginfo/pushlog_client.py
pushlog_client.egg-info/PKG-INFO
pushlog_client.egg-info/SOURCES.txt
pushlog_client.egg-info/dependency_links.txt
pushlog_client.egg-info/requires.txt
pushlog_client.egg-info/top_level.txt