Metadata-Version: 1.0
Name: pushlog-client
Version: 0.6.0
Summary: Script designed to query information about who pushes what where and when.
Home-page: https://hg.mozilla.org/hgcustom/version-control-tools/file/tip/pylib/mozhginfo
Author: Armen Zambrano G.
Author-email: armenzg@mozilla.com
License: MPL2
Platform: UNKNOWN
